[
  {
    "data": "2026-02-01",
    "nome": "ALEX DE SOUZA TAVARES JUNIOR",
    "percentual": 93.55,
    "setor": "ALTA TENSÃO",
    "turno": "1",
    "mes": "Fevereiro"
  },
  {
    "data": "2026-02-01",
    "nome": "ANDERSON BRUNO DE LIMA MORAES",
    "percentual": 75.56,
    "setor": "ALTA TENSÃO",
    "turno": "1",
    "mes": "Fevereiro"
  },
  {
    "data": "2026-02-01",
    "nome": "ANDRESON FERREIRA DA SILVA",
    "percentual": 51.44,
    "setor": "ALTA TENSÃO",
    "turno": "1",
    "mes": "Fevereiro"
  },
  {
    "data": "2026-02-01",
    "nome": "ANTHONY RIBEIRO DIAS",
    "percentual": 46.93,
    "setor": "ALTA TENSÃO",
    "turno": "1",
    "mes": "Fevereiro"
  },
  {
    "data": "2026-02-01",
    "nome": "ANTONIO FERNANDO DOS SANTOS",
    "percentual": 71.53,
    "setor": "ALTA TENSÃO",
    "turno": "2",
    "mes": "Fevereiro"
  },
  {
    "data": "2026-02-01",
    "nome": "BRUNO DA SILVA GEMAQUE",
    "percentual": 36.76,
    "setor": "BAIXA TENSÃO",
    "turno": "1",
    "mes": "Fevereiro"
  },
  {
    "data": "2026-02-01",
    "nome": "CARLOS RAMALHO DA SILVA",
    "percentual": 68.89,
    "setor": "BAIXA TENSÃO",
    "turno": "1",
    "mes": "Fevereiro"
  },
  {
    "data": "2026-02-01",
    "nome": "CLAUDINEI DA SILVA MARIALVA",
    "percentual": 70.29,
    "setor": "ALTA TENSÃO",
    "turno": "2",
    "mes": "Fevereiro"
  },
  {
    "data": "2026-02-01",
    "nome": "CLEUCIVAN FERREIRA COSTA",
    "percentual": 86.26,
    "setor": "BAIXA TENSÃO",
    "turno": "2",
    "mes": "Fevereiro"
  },
  {
    "data": "2026-02-01",
    "nome": "DAVID BRITO SEIXAS",
    "percentual": 86.06,
    "setor": "BAIXA TENSÃO",
    "turno": "1",
    "mes": "Fevereiro"
  },
  {
    "data": "2026-02-01",
    "nome": "DIEGO BANDEIRA RIKER DE SOUSA",
    "percentual": 80.96,
    "setor": "BAIXA TENSÃO",
    "turno": "1",
    "mes": "Fevereiro"
  },
  {
    "data": "2026-02-01",
    "nome": "DIEGO DE OLIVEIRA AMAZONAS",
    "percentual": 32.93,
    "setor": "BAIXA TENSÃO",
    "turno": "2",
    "mes": "Fevereiro"
  },
  {
    "data": "2026-02-01",
    "nome": "EDGLEYSON BATISTA JACAUNA",
    "percentual": 77.76,
    "setor": "ALTA TENSÃO",
    "turno": "1",
    "mes": "Fevereiro"
  },
  {
    "data": "2026-02-01",
    "nome": "EDSON JUNIOR DA SILVA FERREIRA",
    "percentual": 52.85,
    "setor": "BAIXA TENSÃO",
    "turno": "2",
    "mes": "Fevereiro"
  },
  {
    "data": "2026-02-01",
    "nome": "ELDER DOURADO DA SILVA",
    "percentual": 51.95,
    "setor": "ALTA TENSÃO",
    "turno": "2",
    "mes": "Fevereiro"
  },
  {
    "data": "2026-02-01",
    "nome": "ELIAS EMANUEL TAVEIRA NEPOMUCENO",
    "percentual": 79.13,
    "setor": "ALTA TENSÃO",
    "turno": "2",
    "mes": "Fevereiro"
  },
  {
    "data": "2026-02-01",
    "nome": "ELTON DA SILVA ROSAS",
    "percentual": 7.08,
    "setor": "BAIXA TENSÃO",
    "turno": "1",
    "mes": "Fevereiro"
  },
  {
    "data": "2026-02-01",
    "nome": "EMERSON BRUNO PAES SABAT",
    "percentual": 77.48,
    "setor": "BAIXA TENSÃO",
    "turno": "2",
    "mes": "Fevereiro"
  },
  {
    "data": "2026-02-01",
    "nome": "ERICSSON NUNES DE LIMA",
    "percentual": 17.83,
    "setor": "ALTA TENSÃO",
    "turno": "2",
    "mes": "Fevereiro"
  },
  {
    "data": "2026-02-01",
    "nome": "EVERALDO JOSE LIMA DA GRAÇA",
    "percentual": 21.23,
    "setor": "BAIXA TENSÃO",
    "turno": "1",
    "mes": "Fevereiro"
  },
  {
    "data": "2026-02-01",
    "nome": "FREDSON PANTOJA FARIAS",
    "percentual": 64.36,
    "setor": "ALTA TENSÃO",
    "turno": "2",
    "mes": "Fevereiro"
  },
  {
    "data": "2026-02-01",
    "nome": "GAUTIERRE UCHOA SENA",
    "percentual": 32.26,
    "setor": "BAIXA TENSÃO",
    "turno": "1",
    "mes": "Fevereiro"
  },
  {
    "data": "2026-02-01",
    "nome": "GEOVANE LIMA DA SILVA",
    "percentual": 62.25,
    "setor": "BAIXA TENSÃO",
    "turno": "2",
    "mes": "Fevereiro"
  },
  {
    "data": "2026-02-01",
    "nome": "IRANILDO CORREA PAIVA",
    "percentual": 86.56,
    "setor": "BAIXA TENSÃO",
    "turno": "1",
    "mes": "Fevereiro"
  },
  {
    "data": "2026-02-01",
    "nome": "IVERTON CALHEIRO CASTRO",
    "percentual": 71.42,
    "setor": "BAIXA TENSÃO",
    "turno": "2",
    "mes": "Fevereiro"
  },
  {
    "data": "2026-02-01",
    "nome": "JALEEL DOS DANTOS MENDONÇA",
    "percentual": 60.86,
    "setor": "ALTA TENSÃO",
    "turno": "2",
    "mes": "Fevereiro"
  },
  {
    "data": "2026-02-01",
    "nome": "JONATAN SOUZA DA SILVA",
    "percentual": 46.34,
    "setor": "ALTA TENSÃO",
    "turno": "2",
    "mes": "Fevereiro"
  },
  {
    "data": "2026-02-01",
    "nome": "JOSE RODRIGO FERREIRA DO NASCIMENTO",
    "percentual": 52.91,
    "setor": "ALTA TENSÃO",
    "turno": "2",
    "mes": "Fevereiro"
  },
  {
    "data": "2026-02-01",
    "nome": "JOSE TAILO DA COSTA FERREIRA",
    "percentual": 66.35,
    "setor": "ALTA TENSÃO",
    "turno": "1",
    "mes": "Fevereiro"
  },
  {
    "data": "2026-02-01",
    "nome": "JUNILDO AMORIM MESQUITA",
    "percentual": 82.79,
    "setor": "BAIXA TENSÃO",
    "turno": "2",
    "mes": "Fevereiro"
  },
  {
    "data": "2026-02-01",
    "nome": "KENNEDY SANTOS DE MELO",
    "percentual": 76.04,
    "setor": "ALTA TENSÃO",
    "turno": "1",
    "mes": "Fevereiro"
  },
  {
    "data": "2026-02-01",
    "nome": "KRISTOPHER DE SOUZA MARQUES",
    "percentual": 48.28,
    "setor": "ALTA TENSÃO",
    "turno": "2",
    "mes": "Fevereiro"
  },
  {
    "data": "2026-02-01",
    "nome": "LEONARDO ARAUJO DE SOUZA",
    "percentual": 75.35,
    "setor": "ALTA TENSÃO",
    "turno": "2",
    "mes": "Fevereiro"
  },
  {
    "data": "2026-02-01",
    "nome": "LUIS JOSE DE SOUZA CARDOSO",
    "percentual": 46.88,
    "setor": "ALTA TENSÃO",
    "turno": "1",
    "mes": "Fevereiro"
  },
  {
    "data": "2026-02-01",
    "nome": "MANOEL JOSIMAR SOARES DOS ANJOS",
    "percentual": 83.53,
    "setor": "ALTA TENSÃO",
    "turno": "1",
    "mes": "Fevereiro"
  },
  {
    "data": "2026-02-01",
    "nome": "MARCIO GREYK MACEDO DOS SANTOS JUNIOR",
    "percentual": 77.06,
    "setor": "BAIXA TENSÃO",
    "turno": "2",
    "mes": "Fevereiro"
  },
  {
    "data": "2026-02-01",
    "nome": "MARCOS FERNANDES CRUZ",
    "percentual": 88.97,
    "setor": "ALTA TENSÃO",
    "turno": "2",
    "mes": "Fevereiro"
  },
  {
    "data": "2026-02-01",
    "nome": "MATHEUS LUCAS DA SILVA",
    "percentual": 70.58,
    "setor": "ALTA TENSÃO",
    "turno": "1",
    "mes": "Fevereiro"
  },
  {
    "data": "2026-02-01",
    "nome": "MATHEUS NAILSON PINHEIRO DE SOUZA",
    "percentual": 74.63,
    "setor": "ALTA TENSÃO",
    "turno": "1",
    "mes": "Fevereiro"
  },
  {
    "data": "2026-02-01",
    "nome": "MAX DOS SANTOS NASCIMENTO",
    "percentual": 69.14,
    "setor": "ALTA TENSÃO",
    "turno": "1",
    "mes": "Fevereiro"
  },
  {
    "data": "2026-02-01",
    "nome": "MIRLAN DE SOUZA CORREA",
    "percentual": 69.66,
    "setor": "ALTA TENSÃO",
    "turno": "1",
    "mes": "Fevereiro"
  },
  {
    "data": "2026-02-01",
    "nome": "NELDSON SOUZA DA FONSECA",
    "percentual": 86.47,
    "setor": "BAIXA TENSÃO",
    "turno": "1",
    "mes": "Fevereiro"
  },
  {
    "data": "2026-02-01",
    "nome": "PATRICK REIS TAVARES",
    "percentual": 38.35,
    "setor": "BAIXA TENSÃO",
    "turno": "2",
    "mes": "Fevereiro"
  },
  {
    "data": "2026-02-01",
    "nome": "RUAN REGES LIMA",
    "percentual": 79.07,
    "setor": "BAIXA TENSÃO",
    "turno": "1",
    "mes": "Fevereiro"
  },
  {
    "data": "2026-02-01",
    "nome": "THIAGO PRESTES SILVA",
    "percentual": 85.55,
    "setor": "ALTA TENSÃO",
    "turno": "1",
    "mes": "Fevereiro"
  },
  {
    "data": "2026-02-01",
    "nome": "VICTOR HUGO SUDARIO BASTOS",
    "percentual": 73.94,
    "setor": "ALTA TENSÃO",
    "turno": "2",
    "mes": "Fevereiro"
  },
  {
    "data": "2026-02-01",
    "nome": "WALBER MARTINS AZEVEDO",
    "percentual": 74.53,
    "setor": "ALTA TENSÃO",
    "turno": "1",
    "mes": "Fevereiro"
  },
  {
    "data": "2026-02-01",
    "nome": "WALDENEY ELIAS DE LIMA",
    "percentual": 82.6,
    "setor": "BAIXA TENSÃO",
    "turno": "1",
    "mes": "Fevereiro"
  },
  {
    "data": "2026-02-01",
    "nome": "WILLIAN PETRONILHO DE ARAUJO",
    "percentual": 69.93,
    "setor": "ALTA TENSÃO",
    "turno": "1",
    "mes": "Fevereiro"
  },
  {
    "data": "2026-03-01",
    "nome": "ALEX DE SOUZA TAVARES JUNIOR",
    "percentual": 106.7,
    "setor": "ALTA TENSÃO",
    "turno": "1",
    "mes": "Março"
  },
  {
    "data": "2026-03-01",
    "nome": "ANDERSON BRUNO DE LIMA MORAES",
    "percentual": 79.48,
    "setor": "ALTA TENSÃO",
    "turno": "1",
    "mes": "Março"
  },
  {
    "data": "2026-03-01",
    "nome": "ANDRESON FERREIRA DA SILVA",
    "percentual": 62.91,
    "setor": "ALTA TENSÃO",
    "turno": "1",
    "mes": "Março"
  },
  {
    "data": "2026-03-01",
    "nome": "ANTHONY RIBEIRO DIAS",
    "percentual": 58.33,
    "setor": "ALTA TENSÃO",
    "turno": "1",
    "mes": "Março"
  },
  {
    "data": "2026-03-01",
    "nome": "ANTONIO FERNANDO DOS SANTOS",
    "percentual": 91.1,
    "setor": "ALTA TENSÃO",
    "turno": "2",
    "mes": "Março"
  },
  {
    "data": "2026-03-01",
    "nome": "BRUNO DA SILVA GEMAQUE",
    "percentual": 58.46,
    "setor": "BAIXA TENSÃO",
    "turno": "1",
    "mes": "Março"
  },
  {
    "data": "2026-03-01",
    "nome": "CARLOS RAMALHO DA SILVA",
    "percentual": 86.78,
    "setor": "BAIXA TENSÃO",
    "turno": "1",
    "mes": "Março"
  },
  {
    "data": "2026-03-01",
    "nome": "CLAUDINEI DA SILVA MARIALVA",
    "percentual": 77.04,
    "setor": "ALTA TENSÃO",
    "turno": "2",
    "mes": "Março"
  },
  {
    "data": "2026-03-01",
    "nome": "CLEUCIVAN FERREIRA COSTA",
    "percentual": 102.48,
    "setor": "BAIXA TENSÃO",
    "turno": "2",
    "mes": "Março"
  },
  {
    "data": "2026-03-01",
    "nome": "DAVID BRITO SEIXAS",
    "percentual": 95.25,
    "setor": "BAIXA TENSÃO",
    "turno": "1",
    "mes": "Março"
  },
  {
    "data": "2026-03-01",
    "nome": "DIEGO BANDEIRA RIKER DE SOUSA",
    "percentual": 77.54,
    "setor": "BAIXA TENSÃO",
    "turno": "1",
    "mes": "Março"
  },
  {
    "data": "2026-03-01",
    "nome": "DIEGO DE OLIVEIRA AMAZONAS",
    "percentual": 57.77,
    "setor": "BAIXA TENSÃO",
    "turno": "2",
    "mes": "Março"
  },
  {
    "data": "2026-03-01",
    "nome": "EDGLEYSON BATISTA JACAUNA",
    "percentual": 86.8,
    "setor": "ALTA TENSÃO",
    "turno": "1",
    "mes": "Março"
  },
  {
    "data": "2026-03-01",
    "nome": "EDSON JUNIOR DA SILVA FERREIRA",
    "percentual": 51.72,
    "setor": "BAIXA TENSÃO",
    "turno": "2",
    "mes": "Março"
  },
  {
    "data": "2026-03-01",
    "nome": "ELDER DOURADO DA SILVA",
    "percentual": 68.18,
    "setor": "ALTA TENSÃO",
    "turno": "2",
    "mes": "Março"
  },
  {
    "data": "2026-03-01",
    "nome": "ELIAS EMANUEL TAVEIRA NEPOMUCENO",
    "percentual": 108.08,
    "setor": "ALTA TENSÃO",
    "turno": "2",
    "mes": "Março"
  },
  {
    "data": "2026-03-01",
    "nome": "ELTON DA SILVA ROSAS",
    "percentual": 4.25,
    "setor": "BAIXA TENSÃO",
    "turno": "1",
    "mes": "Março"
  },
  {
    "data": "2026-03-01",
    "nome": "EMERSON BRUNO PAES SABAT",
    "percentual": 89.29,
    "setor": "BAIXA TENSÃO",
    "turno": "2",
    "mes": "Março"
  },
  {
    "data": "2026-03-01",
    "nome": "ERICSSON NUNES DE LIMA",
    "percentual": 29.95,
    "setor": "ALTA TENSÃO",
    "turno": "2",
    "mes": "Março"
  },
  {
    "data": "2026-03-01",
    "nome": "FREDSON PANTOJA FARIAS",
    "percentual": 98.78,
    "setor": "ALTA TENSÃO",
    "turno": "2",
    "mes": "Março"
  },
  {
    "data": "2026-03-01",
    "nome": "GAUTIERRE UCHOA SENA",
    "percentual": 59.03,
    "setor": "BAIXA TENSÃO",
    "turno": "1",
    "mes": "Março"
  },
  {
    "data": "2026-03-01",
    "nome": "GEOVANE LIMA DA SILVA",
    "percentual": 82.97,
    "setor": "BAIXA TENSÃO",
    "turno": "2",
    "mes": "Março"
  },
  {
    "data": "2026-03-01",
    "nome": "IRANILDO CORREA PAIVA",
    "percentual": 91.04,
    "setor": "BAIXA TENSÃO",
    "turno": "1",
    "mes": "Março"
  },
  {
    "data": "2026-03-01",
    "nome": "IVERTON CALHEIRO CASTRO",
    "percentual": 20.09,
    "setor": "BAIXA TENSÃO",
    "turno": "2",
    "mes": "Março"
  },
  {
    "data": "2026-03-01",
    "nome": "JALEEL DOS DANTOS MENDONÇA",
    "percentual": 92.14,
    "setor": "ALTA TENSÃO",
    "turno": "2",
    "mes": "Março"
  },
  {
    "data": "2026-03-01",
    "nome": "JOAO PAULO DE SOUZA MEDEIROS",
    "percentual": 41.75,
    "setor": "BAIXA TENSÃO",
    "turno": "1",
    "mes": "Março"
  },
  {
    "data": "2026-03-01",
    "nome": "JONATAN SOUZA DA SILVA",
    "percentual": 81.72,
    "setor": "ALTA TENSÃO",
    "turno": "2",
    "mes": "Março"
  },
  {
    "data": "2026-03-01",
    "nome": "JOSE RODRIGO FERREIRA DO NASCIMENTO",
    "percentual": 79.88,
    "setor": "ALTA TENSÃO",
    "turno": "2",
    "mes": "Março"
  },
  {
    "data": "2026-03-01",
    "nome": "JOSE TAILO DA COSTA FERREIRA",
    "percentual": 55.82,
    "setor": "ALTA TENSÃO",
    "turno": "1",
    "mes": "Março"
  },
  {
    "data": "2026-03-01",
    "nome": "JUNILDO AMORIM MESQUITA",
    "percentual": 101.21,
    "setor": "BAIXA TENSÃO",
    "turno": "2",
    "mes": "Março"
  },
  {
    "data": "2026-03-01",
    "nome": "KENNEDY SANTOS DE MELO",
    "percentual": 80.23,
    "setor": "ALTA TENSÃO",
    "turno": "1",
    "mes": "Março"
  },
  {
    "data": "2026-03-01",
    "nome": "KRISTOPHER DE SOUZA MARQUES",
    "percentual": 57.45,
    "setor": "ALTA TENSÃO",
    "turno": "2",
    "mes": "Março"
  },
  {
    "data": "2026-03-01",
    "nome": "LEONARDO ARAUJO DE SOUZA",
    "percentual": 81.69,
    "setor": "ALTA TENSÃO",
    "turno": "2",
    "mes": "Março"
  },
  {
    "data": "2026-03-01",
    "nome": "LUIS JOSE DE SOUZA CARDOSO",
    "percentual": 37.02,
    "setor": "ALTA TENSÃO",
    "turno": "1",
    "mes": "Março"
  },
  {
    "data": "2026-03-01",
    "nome": "MANOEL JOSIMAR SOARES DOS ANJOS",
    "percentual": 95.26,
    "setor": "ALTA TENSÃO",
    "turno": "1",
    "mes": "Março"
  },
  {
    "data": "2026-03-01",
    "nome": "MARCIO GREYK MACEDO DOS SANTOS JUNIOR",
    "percentual": 91.55,
    "setor": "BAIXA TENSÃO",
    "turno": "2",
    "mes": "Março"
  },
  {
    "data": "2026-03-01",
    "nome": "MARCOS FERNANDES CRUZ",
    "percentual": 107.66,
    "setor": "ALTA TENSÃO",
    "turno": "2",
    "mes": "Março"
  },
  {
    "data": "2026-03-01",
    "nome": "MATHEUS LUCAS DA SILVA",
    "percentual": 88.11,
    "setor": "ALTA TENSÃO",
    "turno": "1",
    "mes": "Março"
  },
  {
    "data": "2026-03-01",
    "nome": "MATHEUS NAILSON PINHEIRO DE SOUZA",
    "percentual": 89.69,
    "setor": "ALTA TENSÃO",
    "turno": "1",
    "mes": "Março"
  },
  {
    "data": "2026-03-01",
    "nome": "MAX DOS SANTOS NASCIMENTO",
    "percentual": 74.37,
    "setor": "ALTA TENSÃO",
    "turno": "1",
    "mes": "Março"
  },
  {
    "data": "2026-03-01",
    "nome": "MIRLAN DE SOUZA CORREA",
    "percentual": 61.99,
    "setor": "ALTA TENSÃO",
    "turno": "1",
    "mes": "Março"
  },
  {
    "data": "2026-03-01",
    "nome": "NELDSON SOUZA DA FONSECA",
    "percentual": 102.76,
    "setor": "BAIXA TENSÃO",
    "turno": "1",
    "mes": "Março"
  },
  {
    "data": "2026-03-01",
    "nome": "PATRICK REIS TAVARES",
    "percentual": 70.29,
    "setor": "BAIXA TENSÃO",
    "turno": "2",
    "mes": "Março"
  },
  {
    "data": "2026-03-01",
    "nome": "RUAN REGES LIMA",
    "percentual": 78.17,
    "setor": "BAIXA TENSÃO",
    "turno": "1",
    "mes": "Março"
  },
  {
    "data": "2026-03-01",
    "nome": "THIAGO PRESTES SILVA",
    "percentual": 106.2,
    "setor": "ALTA TENSÃO",
    "turno": "1",
    "mes": "Março"
  },
  {
    "data": "2026-03-01",
    "nome": "VICTOR HUGO SUDARIO BASTOS",
    "percentual": 58.34,
    "setor": "ALTA TENSÃO",
    "turno": "2",
    "mes": "Março"
  },
  {
    "data": "2026-03-01",
    "nome": "WALBER MARTINS AZEVEDO",
    "percentual": 110.67,
    "setor": "ALTA TENSÃO",
    "turno": "1",
    "mes": "Março"
  },
  {
    "data": "2026-03-01",
    "nome": "WALDENEY ELIAS DE LIMA",
    "percentual": 86.49,
    "setor": "BAIXA TENSÃO",
    "turno": "1",
    "mes": "Março"
  },
  {
    "data": "2026-03-01",
    "nome": "WILLIAN PETRONILHO DE ARAUJO",
    "percentual": 88.88,
    "setor": "ALTA TENSÃO",
    "turno": "1",
    "mes": "Março"
  },
  {
    "data": "2026-04-01",
    "nome": "ALEX DE SOUZA TAVARES JUNIOR",
    "percentual": 107.61,
    "setor": "ALTA TENSÃO",
    "turno": "1",
    "mes": "Abril"
  },
  {
    "data": "2026-04-01",
    "nome": "ANDERSON BRUNO DE LIMA MORAES",
    "percentual": 80.04,
    "setor": "ALTA TENSÃO",
    "turno": "1",
    "mes": "Abril"
  },
  {
    "data": "2026-04-01",
    "nome": "ANDRE VICTOR ANDRADE DA SILVA",
    "percentual": 20.05,
    "setor": "BAIXA TENSÃO",
    "turno": "1",
    "mes": "Abril"
  },
  {
    "data": "2026-04-01",
    "nome": "ANDRESON FERREIRA DA SILVA",
    "percentual": 61.04,
    "setor": "ALTA TENSÃO",
    "turno": "1",
    "mes": "Abril"
  },
  {
    "data": "2026-04-01",
    "nome": "ANTHONY RIBEIRO DIAS",
    "percentual": 55.82,
    "setor": "ALTA TENSÃO",
    "turno": "1",
    "mes": "Abril"
  },
  {
    "data": "2026-04-01",
    "nome": "ANTONIO FERNANDO DOS SANTOS",
    "percentual": 64.29,
    "setor": "ALTA TENSÃO",
    "turno": "2",
    "mes": "Abril"
  },
  {
    "data": "2026-04-01",
    "nome": "BRUNO DA SILVA GEMAQUE",
    "percentual": 61.71,
    "setor": "BAIXA TENSÃO",
    "turno": "1",
    "mes": "Abril"
  },
  {
    "data": "2026-04-01",
    "nome": "CARLOS RAMALHO DA SILVA",
    "percentual": 87.6,
    "setor": "BAIXA TENSÃO",
    "turno": "1",
    "mes": "Abril"
  },
  {
    "data": "2026-04-01",
    "nome": "CLAUDINEI DA SILVA MARIALVA",
    "percentual": 70.1,
    "setor": "ALTA TENSÃO",
    "turno": "2",
    "mes": "Abril"
  },
  {
    "data": "2026-04-01",
    "nome": "CLEUCIVAN FERREIRA COSTA",
    "percentual": 92.84,
    "setor": "BAIXA TENSÃO",
    "turno": "2",
    "mes": "Abril"
  },
  {
    "data": "2026-04-01",
    "nome": "CRISTHOFFER DA SILVA E SILVA",
    "percentual": 57.12,
    "setor": "BAIXA TENSÃO",
    "turno": "2",
    "mes": "Abril"
  },
  {
    "data": "2026-04-01",
    "nome": "DAVID BRITO SEIXAS",
    "percentual": 89.22,
    "setor": "BAIXA TENSÃO",
    "turno": "1",
    "mes": "Abril"
  },
  {
    "data": "2026-04-01",
    "nome": "DAVID JUNIOR DA SILVA MENDONÇA",
    "percentual": 30.75,
    "setor": "ALTA TENSÃO",
    "turno": "1",
    "mes": "Abril"
  },
  {
    "data": "2026-04-01",
    "nome": "DIEGO BANDEIRA RIKER DE SOUSA",
    "percentual": 83.77,
    "setor": "BAIXA TENSÃO",
    "turno": "1",
    "mes": "Abril"
  },
  {
    "data": "2026-04-01",
    "nome": "DIEGO DE OLIVEIRA AMAZONAS",
    "percentual": 63.03,
    "setor": "BAIXA TENSÃO",
    "turno": "2",
    "mes": "Abril"
  },
  {
    "data": "2026-04-01",
    "nome": "EDGLEYSON BATISTA JACAUNA",
    "percentual": 83.23,
    "setor": "ALTA TENSÃO",
    "turno": "1",
    "mes": "Abril"
  },
  {
    "data": "2026-04-01",
    "nome": "EDSON JUNIOR DA SILVA FERREIRA",
    "percentual": 51.44,
    "setor": "BAIXA TENSÃO",
    "turno": "2",
    "mes": "Abril"
  },
  {
    "data": "2026-04-01",
    "nome": "ELDER DOURADO DA SILVA",
    "percentual": 66.2,
    "setor": "ALTA TENSÃO",
    "turno": "2",
    "mes": "Abril"
  },
  {
    "data": "2026-04-01",
    "nome": "ELIAS EMANUEL TAVEIRA NEPOMUCENO",
    "percentual": 84.99,
    "setor": "ALTA TENSÃO",
    "turno": "2",
    "mes": "Abril"
  },
  {
    "data": "2026-04-01",
    "nome": "EMERSON BRUNO PAES SABAT",
    "percentual": 76.44,
    "setor": "BAIXA TENSÃO",
    "turno": "2",
    "mes": "Abril"
  },
  {
    "data": "2026-04-01",
    "nome": "ERICSSON NUNES DE LIMA",
    "percentual": 33.25,
    "setor": "ALTA TENSÃO",
    "turno": "2",
    "mes": "Abril"
  },
  {
    "data": "2026-04-01",
    "nome": "FRANCISCO ALEXANDRE ALVES DE SOUZA",
    "percentual": 50.94,
    "setor": "BAIXA TENSÃO",
    "turno": "1",
    "mes": "Abril"
  },
  {
    "data": "2026-04-01",
    "nome": "FREDSON PANTOJA FARIAS",
    "percentual": 91.3,
    "setor": "ALTA TENSÃO",
    "turno": "2",
    "mes": "Abril"
  },
  {
    "data": "2026-04-01",
    "nome": "GABRIEL BARROS CORREA",
    "percentual": 6.68,
    "setor": "ALTA TENSÃO",
    "turno": "1",
    "mes": "Abril"
  },
  {
    "data": "2026-04-01",
    "nome": "GAUTIERRE UCHOA SENA",
    "percentual": 110.01,
    "setor": "BAIXA TENSÃO",
    "turno": "1",
    "mes": "Abril"
  },
  {
    "data": "2026-04-01",
    "nome": "GEOVANE LIMA DA SILVA",
    "percentual": 85.51,
    "setor": "BAIXA TENSÃO",
    "turno": "2",
    "mes": "Abril"
  },
  {
    "data": "2026-04-01",
    "nome": "IRANILDO CORREA PAIVA",
    "percentual": 83.5,
    "setor": "BAIXA TENSÃO",
    "turno": "1",
    "mes": "Abril"
  },
  {
    "data": "2026-04-01",
    "nome": "IVERTON CALHEIRO CASTRO",
    "percentual": 65.74,
    "setor": "BAIXA TENSÃO",
    "turno": "2",
    "mes": "Abril"
  },
  {
    "data": "2026-04-01",
    "nome": "IVO BRAGA MONTEIRO",
    "percentual": 15.12,
    "setor": "BAIXA TENSÃO",
    "turno": "2",
    "mes": "Abril"
  },
  {
    "data": "2026-04-01",
    "nome": "JALEEL DOS DANTOS MENDONÇA",
    "percentual": 89.99,
    "setor": "ALTA TENSÃO",
    "turno": "2",
    "mes": "Abril"
  },
  {
    "data": "2026-04-01",
    "nome": "JOAO PAULO DE SOUZA MEDEIROS",
    "percentual": 44.52,
    "setor": "BAIXA TENSÃO",
    "turno": "1",
    "mes": "Abril"
  },
  {
    "data": "2026-04-01",
    "nome": "JOAQUIM SABINO RODRIGUES PLACIDO",
    "percentual": 37.73,
    "setor": "BAIXA TENSÃO",
    "turno": "1",
    "mes": "Abril"
  },
  {
    "data": "2026-04-01",
    "nome": "JONATAN SOUZA DA SILVA",
    "percentual": 78.33,
    "setor": "ALTA TENSÃO",
    "turno": "2",
    "mes": "Abril"
  },
  {
    "data": "2026-04-01",
    "nome": "JOSE RODRIGO FERREIRA DO NASCIMENTO",
    "percentual": 66.29,
    "setor": "ALTA TENSÃO",
    "turno": "2",
    "mes": "Abril"
  },
  {
    "data": "2026-04-01",
    "nome": "JOSE TAILO DA COSTA FERREIRA",
    "percentual": 76.42,
    "setor": "ALTA TENSÃO",
    "turno": "1",
    "mes": "Abril"
  },
  {
    "data": "2026-04-01",
    "nome": "JUNILDO AMORIM MESQUITA",
    "percentual": 88.02,
    "setor": "BAIXA TENSÃO",
    "turno": "2",
    "mes": "Abril"
  },
  {
    "data": "2026-04-01",
    "nome": "KENNEDY SANTOS DE MELO",
    "percentual": 85.73,
    "setor": "ALTA TENSÃO",
    "turno": "1",
    "mes": "Abril"
  },
  {
    "data": "2026-04-01",
    "nome": "KRISTOPHER DE SOUZA MARQUES",
    "percentual": 66.36,
    "setor": "ALTA TENSÃO",
    "turno": "2",
    "mes": "Abril"
  },
  {
    "data": "2026-04-01",
    "nome": "LEONARDO ARAUJO DE SOUZA",
    "percentual": 68.72,
    "setor": "ALTA TENSÃO",
    "turno": "2",
    "mes": "Abril"
  },
  {
    "data": "2026-04-01",
    "nome": "MANOEL JOSIMAR SOARES DOS ANJOS",
    "percentual": 89.8,
    "setor": "ALTA TENSÃO",
    "turno": "1",
    "mes": "Abril"
  },
  {
    "data": "2026-04-01",
    "nome": "MARCIO GREYK MACEDO DOS SANTOS JUNIOR",
    "percentual": 77.44,
    "setor": "BAIXA TENSÃO",
    "turno": "2",
    "mes": "Abril"
  },
  {
    "data": "2026-04-01",
    "nome": "MARCOS FERNANDES CRUZ",
    "percentual": 85.64,
    "setor": "ALTA TENSÃO",
    "turno": "2",
    "mes": "Abril"
  },
  {
    "data": "2026-04-01",
    "nome": "MATHEUS LUCAS DA SILVA",
    "percentual": 96.86,
    "setor": "ALTA TENSÃO",
    "turno": "1",
    "mes": "Abril"
  },
  {
    "data": "2026-04-01",
    "nome": "MATHEUS NAILSON PINHEIRO DE SOUZA",
    "percentual": 66.73,
    "setor": "ALTA TENSÃO",
    "turno": "1",
    "mes": "Abril"
  },
  {
    "data": "2026-04-01",
    "nome": "MAX DOS SANTOS NASCIMENTO",
    "percentual": 72.88,
    "setor": "ALTA TENSÃO",
    "turno": "1",
    "mes": "Abril"
  },
  {
    "data": "2026-04-01",
    "nome": "MIRLAN DE SOUZA CORREA",
    "percentual": 64.05,
    "setor": "ALTA TENSÃO",
    "turno": "1",
    "mes": "Abril"
  },
  {
    "data": "2026-04-01",
    "nome": "NELDSON SOUZA DA FONSECA",
    "percentual": 99.74,
    "setor": "BAIXA TENSÃO",
    "turno": "1",
    "mes": "Abril"
  },
  {
    "data": "2026-04-01",
    "nome": "PATRICK REIS TAVARES",
    "percentual": 62.28,
    "setor": "BAIXA TENSÃO",
    "turno": "2",
    "mes": "Abril"
  },
  {
    "data": "2026-04-01",
    "nome": "PERICLES ANGEL MONTEIRO DA SILVA",
    "percentual": 69.1,
    "setor": "ALTA TENSÃO",
    "turno": "1",
    "mes": "Abril"
  },
  {
    "data": "2026-04-01",
    "nome": "RUAN REGES LIMA",
    "percentual": 93.03,
    "setor": "BAIXA TENSÃO",
    "turno": "1",
    "mes": "Abril"
  },
  {
    "data": "2026-04-01",
    "nome": "THIAGO PRESTES SILVA",
    "percentual": 105.34,
    "setor": "ALTA TENSÃO",
    "turno": "1",
    "mes": "Abril"
  },
  {
    "data": "2026-04-01",
    "nome": "VICTOR HUGO SUDARIO BASTOS",
    "percentual": 75.61,
    "setor": "ALTA TENSÃO",
    "turno": "2",
    "mes": "Abril"
  },
  {
    "data": "2026-04-01",
    "nome": "WALBER MARTINS AZEVEDO",
    "percentual": 98.41,
    "setor": "ALTA TENSÃO",
    "turno": "1",
    "mes": "Abril"
  },
  {
    "data": "2026-04-01",
    "nome": "WALDENEY ELIAS DE LIMA",
    "percentual": 83.33,
    "setor": "BAIXA TENSÃO",
    "turno": "1",
    "mes": "Abril"
  },
  {
    "data": "2026-04-01",
    "nome": "WILLIAN PETRONILHO DE ARAUJO",
    "percentual": 69.6,
    "setor": "ALTA TENSÃO",
    "turno": "1",
    "mes": "Abril"
  },
  {
    "data": "2026-05-01",
    "nome": "ALEX DE SOUZA TAVARES JUNIOR",
    "percentual": 100.63,
    "setor": "ALTA TENSÃO",
    "turno": "1",
    "mes": "Maio"
  },
  {
    "data": "2026-05-01",
    "nome": "ANDERSON BRUNO DE LIMA MORAES",
    "percentual": 84.32,
    "setor": "ALTA TENSÃO",
    "turno": "1",
    "mes": "Maio"
  },
  {
    "data": "2026-05-01",
    "nome": "ANDRESON FERREIRA DA SILVA",
    "percentual": 63.23,
    "setor": "ALTA TENSÃO",
    "turno": "1",
    "mes": "Maio"
  },
  {
    "data": "2026-05-01",
    "nome": "ANTHONY RIBEIRO DIAS",
    "percentual": 61.45,
    "setor": "ALTA TENSÃO",
    "turno": "1",
    "mes": "Maio"
  },
  {
    "data": "2026-05-01",
    "nome": "ANTONIO FERNANDO DOS SANTOS",
    "percentual": 84.47,
    "setor": "ALTA TENSÃO",
    "turno": "2",
    "mes": "Maio"
  },
  {
    "data": "2026-05-01",
    "nome": "BRUNO DA SILVA GEMAQUE",
    "percentual": 83.8,
    "setor": "BAIXA TENSÃO",
    "turno": "1",
    "mes": "Maio"
  },
  {
    "data": "2026-05-01",
    "nome": "BRUNO GARCIA DE SOUZA",
    "percentual": 41.88,
    "setor": "BAIXA TENSÃO",
    "turno": "2",
    "mes": "Maio"
  },
  {
    "data": "2026-05-01",
    "nome": "CARLOS RAMALHO DA SILVA",
    "percentual": 89.94,
    "setor": "BAIXA TENSÃO",
    "turno": "1",
    "mes": "Maio"
  },
  {
    "data": "2026-05-01",
    "nome": "CLAUDINEI DA SILVA MARIALVA",
    "percentual": 96.14,
    "setor": "ALTA TENSÃO",
    "turno": "2",
    "mes": "Maio"
  },
  {
    "data": "2026-05-01",
    "nome": "CLEUCIVAN FERREIRA COSTA",
    "percentual": 89.44,
    "setor": "BAIXA TENSÃO",
    "turno": "2",
    "mes": "Maio"
  },
  {
    "data": "2026-05-01",
    "nome": "CRISTHOFFER DA SILVA E SILVA",
    "percentual": 71.96,
    "setor": "BAIXA TENSÃO",
    "turno": "2",
    "mes": "Maio"
  },
  {
    "data": "2026-05-01",
    "nome": "DAVID BRITO SEIXAS",
    "percentual": 82.6,
    "setor": "BAIXA TENSÃO",
    "turno": "1",
    "mes": "Maio"
  },
  {
    "data": "2026-05-01",
    "nome": "DAVID JUNIOR DA SILVA MENDONÇA",
    "percentual": 69.9,
    "setor": "ALTA TENSÃO",
    "turno": "1",
    "mes": "Maio"
  },
  {
    "data": "2026-05-01",
    "nome": "DIEGO BANDEIRA RIKER DE SOUSA",
    "percentual": 82.29,
    "setor": "BAIXA TENSÃO",
    "turno": "1",
    "mes": "Maio"
  },
  {
    "data": "2026-05-01",
    "nome": "DIEGO DE OLIVEIRA AMAZONAS",
    "percentual": 81.4,
    "setor": "BAIXA TENSÃO",
    "turno": "2",
    "mes": "Maio"
  },
  {
    "data": "2026-05-01",
    "nome": "EDGLEYSON BATISTA JACAUNA",
    "percentual": 87.27,
    "setor": "ALTA TENSÃO",
    "turno": "1",
    "mes": "Maio"
  },
  {
    "data": "2026-05-01",
    "nome": "EDSON JUNIOR DA SILVA FERREIRA",
    "percentual": 72.38,
    "setor": "BAIXA TENSÃO",
    "turno": "2",
    "mes": "Maio"
  },
  {
    "data": "2026-05-01",
    "nome": "ELDER DOURADO DA SILVA",
    "percentual": 78.65,
    "setor": "ALTA TENSÃO",
    "turno": "2",
    "mes": "Maio"
  },
  {
    "data": "2026-05-01",
    "nome": "ELIAS EMANUEL TAVEIRA NEPOMUCENO",
    "percentual": 78.76,
    "setor": "ALTA TENSÃO",
    "turno": "2",
    "mes": "Maio"
  },
  {
    "data": "2026-05-01",
    "nome": "EMERSON BRUNO PAES SABAT",
    "percentual": 75.95,
    "setor": "BAIXA TENSÃO",
    "turno": "2",
    "mes": "Maio"
  },
  {
    "data": "2026-05-01",
    "nome": "ERICSSON NUNES DE LIMA",
    "percentual": 38.92,
    "setor": "ALTA TENSÃO",
    "turno": "2",
    "mes": "Maio"
  },
  {
    "data": "2026-05-01",
    "nome": "EVERALDO JOSE LIMA DA GRAÇA",
    "percentual": 74.04,
    "setor": "BAIXA TENSÃO",
    "turno": "1",
    "mes": "Maio"
  },
  {
    "data": "2026-05-01",
    "nome": "FRANCISCO ALEXANDRE ALVES DE SOUZA",
    "percentual": 31.88,
    "setor": "BAIXA TENSÃO",
    "turno": "1",
    "mes": "Maio"
  },
  {
    "data": "2026-05-01",
    "nome": "FREDSON PANTOJA FARIAS",
    "percentual": 82.55,
    "setor": "ALTA TENSÃO",
    "turno": "2",
    "mes": "Maio"
  },
  {
    "data": "2026-05-01",
    "nome": "GABRIEL BARROS CORREA",
    "percentual": 50.55,
    "setor": "ALTA TENSÃO",
    "turno": "1",
    "mes": "Maio"
  },
  {
    "data": "2026-05-01",
    "nome": "GAUTIERRE UCHOA SENA",
    "percentual": 71.19,
    "setor": "BAIXA TENSÃO",
    "turno": "1",
    "mes": "Maio"
  },
  {
    "data": "2026-05-01",
    "nome": "GEOVANE LIMA DA SILVA",
    "percentual": 96.89,
    "setor": "BAIXA TENSÃO",
    "turno": "2",
    "mes": "Maio"
  },
  {
    "data": "2026-05-01",
    "nome": "IRANILDO CORREA PAIVA",
    "percentual": 92.58,
    "setor": "BAIXA TENSÃO",
    "turno": "1",
    "mes": "Maio"
  },
  {
    "data": "2026-05-01",
    "nome": "IVERTON CALHEIRO CASTRO",
    "percentual": 66.02,
    "setor": "BAIXA TENSÃO",
    "turno": "2",
    "mes": "Maio"
  },
  {
    "data": "2026-05-01",
    "nome": "IVO BRAGA MONTEIRO",
    "percentual": 57.45,
    "setor": "BAIXA TENSÃO",
    "turno": "2",
    "mes": "Maio"
  },
  {
    "data": "2026-05-01",
    "nome": "JALEEL DOS DANTOS MENDONÇA",
    "percentual": 84.37,
    "setor": "ALTA TENSÃO",
    "turno": "2",
    "mes": "Maio"
  },
  {
    "data": "2026-05-01",
    "nome": "JOAO PAULO DE SOUZA MEDEIROS",
    "percentual": 53.63,
    "setor": "BAIXA TENSÃO",
    "turno": "1",
    "mes": "Maio"
  },
  {
    "data": "2026-05-01",
    "nome": "JOAQUIM SABINO RODRIGUES PLACIDO",
    "percentual": 71.53,
    "setor": "BAIXA TENSÃO",
    "turno": "1",
    "mes": "Maio"
  },
  {
    "data": "2026-05-01",
    "nome": "JONATAN SOUZA DA SILVA",
    "percentual": 78.83,
    "setor": "ALTA TENSÃO",
    "turno": "2",
    "mes": "Maio"
  },
  {
    "data": "2026-05-01",
    "nome": "JOSE RODRIGO FERREIRA DO NASCIMENTO",
    "percentual": 82.78,
    "setor": "ALTA TENSÃO",
    "turno": "2",
    "mes": "Maio"
  },
  {
    "data": "2026-05-01",
    "nome": "JUNILDO AMORIM MESQUITA",
    "percentual": 96.11,
    "setor": "BAIXA TENSÃO",
    "turno": "2",
    "mes": "Maio"
  },
  {
    "data": "2026-05-01",
    "nome": "KENNEDY SANTOS DE MELO",
    "percentual": 94.63,
    "setor": "ALTA TENSÃO",
    "turno": "1",
    "mes": "Maio"
  },
  {
    "data": "2026-05-01",
    "nome": "KRISTOPHER DE SOUZA MARQUES",
    "percentual": 73.96,
    "setor": "ALTA TENSÃO",
    "turno": "2",
    "mes": "Maio"
  },
  {
    "data": "2026-05-01",
    "nome": "LAZARO",
    "percentual": 45.0,
    "setor": "ALTA TENSÃO",
    "turno": "1",
    "mes": "Maio"
  },
  {
    "data": "2026-05-01",
    "nome": "LEONARDO ARAUJO DE SOUZA",
    "percentual": 94.86,
    "setor": "ALTA TENSÃO",
    "turno": "2",
    "mes": "Maio"
  },
  {
    "data": "2026-05-01",
    "nome": "MANOEL JOSIMAR SOARES DOS ANJOS",
    "percentual": 96.71,
    "setor": "ALTA TENSÃO",
    "turno": "1",
    "mes": "Maio"
  },
  {
    "data": "2026-05-01",
    "nome": "MARCIO GREYK MACEDO DOS SANTOS JUNIOR",
    "percentual": 93.02,
    "setor": "BAIXA TENSÃO",
    "turno": "2",
    "mes": "Maio"
  },
  {
    "data": "2026-05-01",
    "nome": "MARCOS FERNANDES CRUZ",
    "percentual": 81.35,
    "setor": "ALTA TENSÃO",
    "turno": "2",
    "mes": "Maio"
  },
  {
    "data": "2026-05-01",
    "nome": "MATHEUS LUCAS DA SILVA",
    "percentual": 94.83,
    "setor": "ALTA TENSÃO",
    "turno": "1",
    "mes": "Maio"
  },
  {
    "data": "2026-05-01",
    "nome": "MATHEUS NAILSON PINHEIRO DE SOUZA",
    "percentual": 85.34,
    "setor": "ALTA TENSÃO",
    "turno": "1",
    "mes": "Maio"
  },
  {
    "data": "2026-05-01",
    "nome": "MAX DOS SANTOS NASCIMENTO",
    "percentual": 92.57,
    "setor": "ALTA TENSÃO",
    "turno": "1",
    "mes": "Maio"
  },
  {
    "data": "2026-05-01",
    "nome": "MIRLAN DE SOUZA CORREA",
    "percentual": 65.59,
    "setor": "ALTA TENSÃO",
    "turno": "1",
    "mes": "Maio"
  },
  {
    "data": "2026-05-01",
    "nome": "NELDSON SOUZA DA FONSECA",
    "percentual": 91.26,
    "setor": "BAIXA TENSÃO",
    "turno": "1",
    "mes": "Maio"
  },
  {
    "data": "2026-05-01",
    "nome": "PATRICK REIS TAVARES",
    "percentual": 68.51,
    "setor": "BAIXA TENSÃO",
    "turno": "2",
    "mes": "Maio"
  },
  {
    "data": "2026-05-01",
    "nome": "PERICLES ANGEL MONTEIRO DA SILVA",
    "percentual": 75.17,
    "setor": "ALTA TENSÃO",
    "turno": "1",
    "mes": "Maio"
  },
  {
    "data": "2026-05-01",
    "nome": "RUAN REGES LIMA",
    "percentual": 76.5,
    "setor": "BAIXA TENSÃO",
    "turno": "1",
    "mes": "Maio"
  },
  {
    "data": "2026-05-01",
    "nome": "THIAGO PRESTES SILVA",
    "percentual": 103.35,
    "setor": "ALTA TENSÃO",
    "turno": "1",
    "mes": "Maio"
  },
  {
    "data": "2026-05-01",
    "nome": "VICTOR HUGO SUDARIO BASTOS",
    "percentual": 72.81,
    "setor": "ALTA TENSÃO",
    "turno": "2",
    "mes": "Maio"
  },
  {
    "data": "2026-05-01",
    "nome": "WALBER MARTINS AZEVEDO",
    "percentual": 98.19,
    "setor": "ALTA TENSÃO",
    "turno": "1",
    "mes": "Maio"
  },
  {
    "data": "2026-05-01",
    "nome": "WALDENEY ELIAS DE LIMA",
    "percentual": 78.47,
    "setor": "BAIXA TENSÃO",
    "turno": "1",
    "mes": "Maio"
  },
  {
    "data": "2026-05-01",
    "nome": "WILLIAN PETRONILHO DE ARAUJO",
    "percentual": 75.94,
    "setor": "ALTA TENSÃO",
    "turno": "1",
    "mes": "Maio"
  },
  {
    "data": "2026-06-01",
    "nome": "ALEX DE SOUZA TAVARES JUNIOR",
    "percentual": 113.63,
    "setor": "ALTA TENSÃO",
    "turno": "1",
    "mes": "Junho"
  },
  {
    "data": "2026-06-01",
    "nome": "ANDERSON BRUNO DE LIMA MORAES",
    "percentual": 89.47,
    "setor": "ALTA TENSÃO",
    "turno": "1",
    "mes": "Junho"
  },
  {
    "data": "2026-06-01",
    "nome": "ANDRESON FERREIRA DA SILVA",
    "percentual": 60.66,
    "setor": "ALTA TENSÃO",
    "turno": "1",
    "mes": "Junho"
  },
  {
    "data": "2026-06-01",
    "nome": "ANDREY",
    "percentual": 57.12,
    "setor": "BAIXA TENSÃO",
    "turno": "2",
    "mes": "Junho"
  },
  {
    "data": "2026-06-01",
    "nome": "ANTHONY RIBEIRO DIAS",
    "percentual": 47.41,
    "setor": "ALTA TENSÃO",
    "turno": "1",
    "mes": "Junho"
  },
  {
    "data": "2026-06-01",
    "nome": "ANTONIO FERNANDO DOS SANTOS",
    "percentual": 94.38,
    "setor": "ALTA TENSÃO",
    "turno": "2",
    "mes": "Junho"
  },
  {
    "data": "2026-06-01",
    "nome": "BRUNO DA SILVA GEMAQUE",
    "percentual": 71.19,
    "setor": "BAIXA TENSÃO",
    "turno": "1",
    "mes": "Junho"
  },
  {
    "data": "2026-06-01",
    "nome": "BRUNO GARCIA DE SOUZA",
    "percentual": 56.83,
    "setor": "BAIXA TENSÃO",
    "turno": "2",
    "mes": "Junho"
  },
  {
    "data": "2026-06-01",
    "nome": "CARLOS RAMALHO DA SILVA",
    "percentual": 88.33,
    "setor": "BAIXA TENSÃO",
    "turno": "1",
    "mes": "Junho"
  },
  {
    "data": "2026-06-01",
    "nome": "CLAUDINEI DA SILVA MARIALVA",
    "percentual": 103.11,
    "setor": "ALTA TENSÃO",
    "turno": "2",
    "mes": "Junho"
  },
  {
    "data": "2026-06-01",
    "nome": "CLEUCIVAN FERREIRA COSTA",
    "percentual": 86.49,
    "setor": "BAIXA TENSÃO",
    "turno": "2",
    "mes": "Junho"
  },
  {
    "data": "2026-06-01",
    "nome": "CRISTHOFFER DA SILVA E SILVA",
    "percentual": 88.88,
    "setor": "BAIXA TENSÃO",
    "turno": "2",
    "mes": "Junho"
  },
  {
    "data": "2026-06-01",
    "nome": "DAVID BRITO SEIXAS",
    "percentual": 86.53,
    "setor": "BAIXA TENSÃO",
    "turno": "1",
    "mes": "Junho"
  },
  {
    "data": "2026-06-01",
    "nome": "DAVID JUNIOR DA SILVA MENDONÇA",
    "percentual": 77.36,
    "setor": "ALTA TENSÃO",
    "turno": "1",
    "mes": "Junho"
  },
  {
    "data": "2026-06-01",
    "nome": "DIEGO BANDEIRA RIKER DE SOUSA",
    "percentual": 82.04,
    "setor": "BAIXA TENSÃO",
    "turno": "1",
    "mes": "Junho"
  },
  {
    "data": "2026-06-01",
    "nome": "EDGLEYSON BATISTA JACAUNA",
    "percentual": 91.83,
    "setor": "ALTA TENSÃO",
    "turno": "1",
    "mes": "Junho"
  },
  {
    "data": "2026-06-01",
    "nome": "EDSON JUNIOR DA SILVA FERREIRA",
    "percentual": 66.11,
    "setor": "BAIXA TENSÃO",
    "turno": "2",
    "mes": "Junho"
  },
  {
    "data": "2026-06-01",
    "nome": "ELDER DOURADO DA SILVA",
    "percentual": 83.17,
    "setor": "ALTA TENSÃO",
    "turno": "2",
    "mes": "Junho"
  },
  {
    "data": "2026-06-01",
    "nome": "ELIAS EMANUEL TAVEIRA NEPOMUCENO",
    "percentual": 85.24,
    "setor": "ALTA TENSÃO",
    "turno": "2",
    "mes": "Junho"
  },
  {
    "data": "2026-06-01",
    "nome": "EMERSON BRUNO PAES SABAT",
    "percentual": 64.9,
    "setor": "BAIXA TENSÃO",
    "turno": "2",
    "mes": "Junho"
  },
  {
    "data": "2026-06-01",
    "nome": "ERICSSON NUNES DE LIMA",
    "percentual": 39.49,
    "setor": "ALTA TENSÃO",
    "turno": "2",
    "mes": "Junho"
  },
  {
    "data": "2026-06-01",
    "nome": "FRANCISCO ALEXANDRE ALVES DE SOUZA",
    "percentual": 53.82,
    "setor": "BAIXA TENSÃO",
    "turno": "1",
    "mes": "Junho"
  },
  {
    "data": "2026-06-01",
    "nome": "FREDSON PANTOJA FARIAS",
    "percentual": 84.48,
    "setor": "ALTA TENSÃO",
    "turno": "2",
    "mes": "Junho"
  },
  {
    "data": "2026-06-01",
    "nome": "GABRIEL BARROS CORREA",
    "percentual": 62.57,
    "setor": "ALTA TENSÃO",
    "turno": "1",
    "mes": "Junho"
  },
  {
    "data": "2026-06-01",
    "nome": "GAUTIERRE UCHOA SENA",
    "percentual": 75.87,
    "setor": "BAIXA TENSÃO",
    "turno": "1",
    "mes": "Junho"
  },
  {
    "data": "2026-06-01",
    "nome": "GEOVANE LIMA DA SILVA",
    "percentual": 92.57,
    "setor": "BAIXA TENSÃO",
    "turno": "2",
    "mes": "Junho"
  },
  {
    "data": "2026-06-01",
    "nome": "IRANILDO CORREA PAIVA",
    "percentual": 72.51,
    "setor": "BAIXA TENSÃO",
    "turno": "1",
    "mes": "Junho"
  },
  {
    "data": "2026-06-01",
    "nome": "IVERTON CALHEIRO CASTRO",
    "percentual": 80.33,
    "setor": "BAIXA TENSÃO",
    "turno": "2",
    "mes": "Junho"
  },
  {
    "data": "2026-06-01",
    "nome": "IVO BRAGA MONTEIRO",
    "percentual": 47.68,
    "setor": "BAIXA TENSÃO",
    "turno": "2",
    "mes": "Junho"
  },
  {
    "data": "2026-06-01",
    "nome": "JALEEL DOS DANTOS MENDONÇA",
    "percentual": 97.69,
    "setor": "ALTA TENSÃO",
    "turno": "2",
    "mes": "Junho"
  },
  {
    "data": "2026-06-01",
    "nome": "JOAO PAULO DE SOUZA MEDEIROS",
    "percentual": 52.32,
    "setor": "BAIXA TENSÃO",
    "turno": "1",
    "mes": "Junho"
  },
  {
    "data": "2026-06-01",
    "nome": "JONATAN SOUZA DA SILVA",
    "percentual": 90.01,
    "setor": "ALTA TENSÃO",
    "turno": "2",
    "mes": "Junho"
  },
  {
    "data": "2026-06-01",
    "nome": "JOSE RODRIGO FERREIRA DO NASCIMENTO",
    "percentual": 86.12,
    "setor": "ALTA TENSÃO",
    "turno": "2",
    "mes": "Junho"
  },
  {
    "data": "2026-06-01",
    "nome": "JUNILDO AMORIM MESQUITA",
    "percentual": 76.01,
    "setor": "BAIXA TENSÃO",
    "turno": "2",
    "mes": "Junho"
  },
  {
    "data": "2026-06-01",
    "nome": "KENNEDY SANTOS DE MELO",
    "percentual": 105.53,
    "setor": "ALTA TENSÃO",
    "turno": "1",
    "mes": "Junho"
  },
  {
    "data": "2026-06-01",
    "nome": "KRISTOPHER DE SOUZA MARQUES",
    "percentual": 61.96,
    "setor": "ALTA TENSÃO",
    "turno": "2",
    "mes": "Junho"
  },
  {
    "data": "2026-06-01",
    "nome": "LAZARO",
    "percentual": 51.53,
    "setor": "ALTA TENSÃO",
    "turno": "1",
    "mes": "Junho"
  },
  {
    "data": "2026-06-01",
    "nome": "LEONARDO ARAUJO DE SOUZA",
    "percentual": 89.51,
    "setor": "ALTA TENSÃO",
    "turno": "2",
    "mes": "Junho"
  },
  {
    "data": "2026-06-01",
    "nome": "MANOEL JOSIMAR SOARES DOS ANJOS",
    "percentual": 93.42,
    "setor": "ALTA TENSÃO",
    "turno": "1",
    "mes": "Junho"
  },
  {
    "data": "2026-06-01",
    "nome": "MARCIO GREYK MACEDO DOS SANTOS JUNIOR",
    "percentual": 88.85,
    "setor": "BAIXA TENSÃO",
    "turno": "2",
    "mes": "Junho"
  },
  {
    "data": "2026-06-01",
    "nome": "MARCOS FERNANDES CRUZ",
    "percentual": 96.75,
    "setor": "ALTA TENSÃO",
    "turno": "2",
    "mes": "Junho"
  },
  {
    "data": "2026-06-01",
    "nome": "MATHEUS LUCAS DA SILVA",
    "percentual": 96.05,
    "setor": "ALTA TENSÃO",
    "turno": "1",
    "mes": "Junho"
  },
  {
    "data": "2026-06-01",
    "nome": "MATHEUS NAILSON PINHEIRO DE SOUZA",
    "percentual": 72.55,
    "setor": "ALTA TENSÃO",
    "turno": "1",
    "mes": "Junho"
  },
  {
    "data": "2026-06-01",
    "nome": "MAX DOS SANTOS NASCIMENTO",
    "percentual": 100.29,
    "setor": "ALTA TENSÃO",
    "turno": "1",
    "mes": "Junho"
  },
  {
    "data": "2026-06-01",
    "nome": "MIRLAN DE SOUZA CORREA",
    "percentual": 62.41,
    "setor": "ALTA TENSÃO",
    "turno": "1",
    "mes": "Junho"
  },
  {
    "data": "2026-06-01",
    "nome": "NELDSON SOUZA DA FONSECA",
    "percentual": 84.05,
    "setor": "BAIXA TENSÃO",
    "turno": "1",
    "mes": "Junho"
  },
  {
    "data": "2026-06-01",
    "nome": "PATRICK REIS TAVARES",
    "percentual": 54.35,
    "setor": "BAIXA TENSÃO",
    "turno": "2",
    "mes": "Junho"
  },
  {
    "data": "2026-06-01",
    "nome": "PERICLES ANGEL MONTEIRO DA SILVA",
    "percentual": 84.81,
    "setor": "ALTA TENSÃO",
    "turno": "1",
    "mes": "Junho"
  },
  {
    "data": "2026-06-01",
    "nome": "RUAN REGES LIMA",
    "percentual": 80.1,
    "setor": "BAIXA TENSÃO",
    "turno": "1",
    "mes": "Junho"
  },
  {
    "data": "2026-06-01",
    "nome": "SILVANA",
    "percentual": 54.59,
    "setor": "ALTA TENSÃO",
    "turno": "2",
    "mes": "Junho"
  },
  {
    "data": "2026-06-01",
    "nome": "THIAGO PRESTES SILVA",
    "percentual": 114.4,
    "setor": "ALTA TENSÃO",
    "turno": "1",
    "mes": "Junho"
  },
  {
    "data": "2026-06-01",
    "nome": "VICTOR HUGO SUDARIO BASTOS",
    "percentual": 91.56,
    "setor": "ALTA TENSÃO",
    "turno": "2",
    "mes": "Junho"
  },
  {
    "data": "2026-06-01",
    "nome": "WALBER MARTINS AZEVEDO",
    "percentual": 112.86,
    "setor": "ALTA TENSÃO",
    "turno": "1",
    "mes": "Junho"
  },
  {
    "data": "2026-06-01",
    "nome": "WALDENEY ELIAS DE LIMA",
    "percentual": 85.74,
    "setor": "BAIXA TENSÃO",
    "turno": "1",
    "mes": "Junho"
  },
  {
    "data": "2026-06-01",
    "nome": "WILLIAN PETRONILHO DE ARAUJO",
    "percentual": 92.2,
    "setor": "ALTA TENSÃO",
    "turno": "1",
    "mes": "Junho"
  },
  {
    "data": "2026-07-01",
    "nome": "ALEX DE SOUZA TAVARES JUNIOR",
    "percentual": 109.62,
    "setor": "ALTA TENSÃO",
    "turno": "1",
    "mes": "Julho"
  },
  {
    "data": "2026-07-01",
    "nome": "ANDERSON BRUNO DE LIMA MORAES",
    "percentual": 83.58,
    "setor": "ALTA TENSÃO",
    "turno": "1",
    "mes": "Julho"
  },
  {
    "data": "2026-07-01",
    "nome": "ANDRESON FERREIRA DA SILVA",
    "percentual": 82.11,
    "setor": "ALTA TENSÃO",
    "turno": "1",
    "mes": "Julho"
  },
  {
    "data": "2026-07-01",
    "nome": "ANDREY",
    "percentual": 48.34,
    "setor": "BAIXA TENSÃO",
    "turno": "2",
    "mes": "Julho"
  },
  {
    "data": "2026-07-01",
    "nome": "ANTHONY RIBEIRO DIAS",
    "percentual": 71.02,
    "setor": "ALTA TENSÃO",
    "turno": "1",
    "mes": "Julho"
  },
  {
    "data": "2026-07-01",
    "nome": "ANTONIO FERNANDO DOS SANTOS",
    "percentual": 89.52,
    "setor": "ALTA TENSÃO",
    "turno": "2",
    "mes": "Julho"
  },
  {
    "data": "2026-07-01",
    "nome": "BRUNO DA SILVA GEMAQUE",
    "percentual": 87.91,
    "setor": "BAIXA TENSÃO",
    "turno": "1",
    "mes": "Julho"
  },
  {
    "data": "2026-07-01",
    "nome": "BRUNO GARCIA DE SOUZA",
    "percentual": 49.06,
    "setor": "BAIXA TENSÃO",
    "turno": "2",
    "mes": "Julho"
  },
  {
    "data": "2026-07-01",
    "nome": "CARLOS RAMALHO DA SILVA",
    "percentual": 94.02,
    "setor": "BAIXA TENSÃO",
    "turno": "1",
    "mes": "Julho"
  },
  {
    "data": "2026-07-01",
    "nome": "CLAUDINEI DA SILVA MARIALVA",
    "percentual": 79.03,
    "setor": "ALTA TENSÃO",
    "turno": "2",
    "mes": "Julho"
  },
  {
    "data": "2026-07-01",
    "nome": "CLEUCIVAN FERREIRA COSTA",
    "percentual": 92.87,
    "setor": "BAIXA TENSÃO",
    "turno": "2",
    "mes": "Julho"
  },
  {
    "data": "2026-07-01",
    "nome": "CRISTHOFFER DA SILVA E SILVA",
    "percentual": 90.72,
    "setor": "BAIXA TENSÃO",
    "turno": "2",
    "mes": "Julho"
  },
  {
    "data": "2026-07-01",
    "nome": "DAVID BRITO SEIXAS",
    "percentual": 88.64,
    "setor": "BAIXA TENSÃO",
    "turno": "1",
    "mes": "Julho"
  },
  {
    "data": "2026-07-01",
    "nome": "DAVID JUNIOR DA SILVA MENDONÇA",
    "percentual": 64.37,
    "setor": "ALTA TENSÃO",
    "turno": "1",
    "mes": "Julho"
  },
  {
    "data": "2026-07-01",
    "nome": "DIEGO BANDEIRA RIKER DE SOUSA",
    "percentual": 81.77,
    "setor": "BAIXA TENSÃO",
    "turno": "1",
    "mes": "Julho"
  },
  {
    "data": "2026-07-01",
    "nome": "EDGLEYSON BATISTA JACAUNA",
    "percentual": 60.33,
    "setor": "ALTA TENSÃO",
    "turno": "1",
    "mes": "Julho"
  },
  {
    "data": "2026-07-01",
    "nome": "ELDER DOURADO DA SILVA",
    "percentual": 78.76,
    "setor": "ALTA TENSÃO",
    "turno": "2",
    "mes": "Julho"
  },
  {
    "data": "2026-07-01",
    "nome": "ELTON",
    "percentual": 28.57,
    "setor": "BAIXA TENSÃO",
    "turno": "2",
    "mes": "Julho"
  },
  {
    "data": "2026-07-01",
    "nome": "EMERSON BRUNO PAES SABAT",
    "percentual": 67.06,
    "setor": "BAIXA TENSÃO",
    "turno": "2",
    "mes": "Julho"
  },
  {
    "data": "2026-07-01",
    "nome": "ERICSSON NUNES DE LIMA",
    "percentual": 38.58,
    "setor": "ALTA TENSÃO",
    "turno": "2",
    "mes": "Julho"
  },
  {
    "data": "2026-07-01",
    "nome": "FRANCISCO ALEXANDRE ALVES DE SOUZA",
    "percentual": 55.68,
    "setor": "BAIXA TENSÃO",
    "turno": "1",
    "mes": "Julho"
  },
  {
    "data": "2026-07-01",
    "nome": "FREDSON PANTOJA FARIAS",
    "percentual": 59.78,
    "setor": "ALTA TENSÃO",
    "turno": "2",
    "mes": "Julho"
  },
  {
    "data": "2026-07-01",
    "nome": "GABRIEL BARROS CORREA",
    "percentual": 68.7,
    "setor": "ALTA TENSÃO",
    "turno": "1",
    "mes": "Julho"
  },
  {
    "data": "2026-07-01",
    "nome": "GAUTIERRE UCHOA SENA",
    "percentual": 77.51,
    "setor": "BAIXA TENSÃO",
    "turno": "1",
    "mes": "Julho"
  },
  {
    "data": "2026-07-01",
    "nome": "GEOVANE LIMA DA SILVA",
    "percentual": 82.78,
    "setor": "BAIXA TENSÃO",
    "turno": "2",
    "mes": "Julho"
  },
  {
    "data": "2026-07-01",
    "nome": "GEOVANI",
    "percentual": 66.22,
    "setor": "BAIXA TENSÃO",
    "turno": "1",
    "mes": "Julho"
  },
  {
    "data": "2026-07-01",
    "nome": "IVERTON CALHEIRO CASTRO",
    "percentual": 68.49,
    "setor": "BAIXA TENSÃO",
    "turno": "2",
    "mes": "Julho"
  },
  {
    "data": "2026-07-01",
    "nome": "IVO BRAGA MONTEIRO",
    "percentual": 69.94,
    "setor": "BAIXA TENSÃO",
    "turno": "2",
    "mes": "Julho"
  },
  {
    "data": "2026-07-01",
    "nome": "JALEEL DOS DANTOS MENDONÇA",
    "percentual": 71.31,
    "setor": "ALTA TENSÃO",
    "turno": "2",
    "mes": "Julho"
  },
  {
    "data": "2026-07-01",
    "nome": "JOAO PAULO DE SOUZA MEDEIROS",
    "percentual": 26.7,
    "setor": "BAIXA TENSÃO",
    "turno": "1",
    "mes": "Julho"
  },
  {
    "data": "2026-07-01",
    "nome": "JONATAN SOUZA DA SILVA",
    "percentual": 84.01,
    "setor": "ALTA TENSÃO",
    "turno": "2",
    "mes": "Julho"
  },
  {
    "data": "2026-07-01",
    "nome": "JOSE RODRIGO FERREIRA DO NASCIMENTO",
    "percentual": 87.45,
    "setor": "ALTA TENSÃO",
    "turno": "2",
    "mes": "Julho"
  },
  {
    "data": "2026-07-01",
    "nome": "JUNILDO AMORIM MESQUITA",
    "percentual": 83.49,
    "setor": "BAIXA TENSÃO",
    "turno": "2",
    "mes": "Julho"
  },
  {
    "data": "2026-07-01",
    "nome": "KENNEDY SANTOS DE MELO",
    "percentual": 97.47,
    "setor": "ALTA TENSÃO",
    "turno": "1",
    "mes": "Julho"
  },
  {
    "data": "2026-07-01",
    "nome": "KRISTOPHER DE SOUZA MARQUES",
    "percentual": 67.55,
    "setor": "ALTA TENSÃO",
    "turno": "2",
    "mes": "Julho"
  },
  {
    "data": "2026-07-01",
    "nome": "LAZARO",
    "percentual": 71.91,
    "setor": "ALTA TENSÃO",
    "turno": "1",
    "mes": "Julho"
  },
  {
    "data": "2026-07-01",
    "nome": "LEONARDO ARAUJO DE SOUZA",
    "percentual": 78.36,
    "setor": "ALTA TENSÃO",
    "turno": "2",
    "mes": "Julho"
  },
  {
    "data": "2026-07-01",
    "nome": "MANOEL JOSIMAR SOARES DOS ANJOS",
    "percentual": 91.31,
    "setor": "ALTA TENSÃO",
    "turno": "1",
    "mes": "Julho"
  },
  {
    "data": "2026-07-01",
    "nome": "MARCIO GREYK MACEDO DOS SANTOS JUNIOR",
    "percentual": 86.8,
    "setor": "BAIXA TENSÃO",
    "turno": "2",
    "mes": "Julho"
  },
  {
    "data": "2026-07-01",
    "nome": "MARCOS FERNANDES CRUZ",
    "percentual": 89.93,
    "setor": "ALTA TENSÃO",
    "turno": "2",
    "mes": "Julho"
  },
  {
    "data": "2026-07-01",
    "nome": "MATHEUS LUCAS DA SILVA",
    "percentual": 46.34,
    "setor": "ALTA TENSÃO",
    "turno": "1",
    "mes": "Julho"
  },
  {
    "data": "2026-07-01",
    "nome": "MATHEUS NAILSON PINHEIRO DE SOUZA",
    "percentual": 72.32,
    "setor": "ALTA TENSÃO",
    "turno": "1",
    "mes": "Julho"
  },
  {
    "data": "2026-07-01",
    "nome": "MAX DOS SANTOS NASCIMENTO",
    "percentual": 100.58,
    "setor": "ALTA TENSÃO",
    "turno": "1",
    "mes": "Julho"
  },
  {
    "data": "2026-07-01",
    "nome": "MICHEL",
    "percentual": 22.89,
    "setor": "BAIXA TENSÃO",
    "turno": "2",
    "mes": "Julho"
  },
  {
    "data": "2026-07-01",
    "nome": "MIRLAN DE SOUZA CORREA",
    "percentual": 87.19,
    "setor": "ALTA TENSÃO",
    "turno": "1",
    "mes": "Julho"
  },
  {
    "data": "2026-07-01",
    "nome": "NELDSON SOUZA DA FONSECA",
    "percentual": 73.76,
    "setor": "BAIXA TENSÃO",
    "turno": "1",
    "mes": "Julho"
  },
  {
    "data": "2026-07-01",
    "nome": "PATRICK REIS TAVARES",
    "percentual": 30.0,
    "setor": "BAIXA TENSÃO",
    "turno": "2",
    "mes": "Julho"
  },
  {
    "data": "2026-07-01",
    "nome": "PERICLES ANGEL MONTEIRO DA SILVA",
    "percentual": 70.19,
    "setor": "ALTA TENSÃO",
    "turno": "1",
    "mes": "Julho"
  },
  {
    "data": "2026-07-01",
    "nome": "RUAN REGES LIMA",
    "percentual": 63.07,
    "setor": "BAIXA TENSÃO",
    "turno": "1",
    "mes": "Julho"
  },
  {
    "data": "2026-07-01",
    "nome": "THIAGO PRESTES SILVA",
    "percentual": 101.69,
    "setor": "ALTA TENSÃO",
    "turno": "1",
    "mes": "Julho"
  },
  {
    "data": "2026-07-01",
    "nome": "VICTOR HUGO SUDARIO BASTOS",
    "percentual": 78.02,
    "setor": "ALTA TENSÃO",
    "turno": "2",
    "mes": "Julho"
  },
  {
    "data": "2026-07-01",
    "nome": "WALBER MARTINS AZEVEDO",
    "percentual": 111.08,
    "setor": "ALTA TENSÃO",
    "turno": "1",
    "mes": "Julho"
  },
  {
    "data": "2026-07-01",
    "nome": "WALDENEY ELIAS DE LIMA",
    "percentual": 82.01,
    "setor": "BAIXA TENSÃO",
    "turno": "1",
    "mes": "Julho"
  },
  {
    "data": "2026-07-01",
    "nome": "WILLIAN PETRONILHO DE ARAUJO",
    "percentual": 89.03,
    "setor": "ALTA TENSÃO",
    "turno": "1",
    "mes": "Julho"
  }
]